image2sound/__init__.py
image2sound/cli.py
image2sound/compose.py
image2sound/features.py
image2sound/mapping.py
image2sound/synth.py
image2sound/ui.py
image2sound/utils.py
image2sound_newrealm-0.5.1.dist-info/licenses/LICENSE
image2sound_newrealm-0.5.1.dist-info/METADATA
image2sound_newrealm-0.5.1.dist-info/WHEEL
image2sound_newrealm-0.5.1.dist-info/entry_points.txt
image2sound_newrealm-0.5.1.dist-info/top_level.txt
image2sound_newrealm-0.5.1.dist-info/RECORD
