Metadata-Version: 2.4
Name: image2sound-newrealm
Version: 0.5.1
Summary: Turn images into short musical pieces via algorithmic sonification.
Author-email: Rami Pinku <rami@newrelam.co>
License-Expression: Apache-2.0
Project-URL: Repository, https://github.com/newrealmco/image2sound
Project-URL: Issues, https://github.com/newrealmco/image2sound/issues
Project-URL: Changelog, https://github.com/newrealmco/image2sound/releases
Keywords: audio,music,sonification,image,ai,gradio
Classifier: Development Status :: 3 - Alpha
Classifier: Intended Audience :: End Users/Desktop
Classifier: Operating System :: OS Independent
Classifier: Programming Language :: Python :: 3
Classifier: Programming Language :: Python :: 3.11
Classifier: Programming Language :: Python :: 3.12
Classifier: Environment :: Console
Classifier: Topic :: Multimedia :: Sound/Audio
Requires-Python: >=3.10
License-File: LICENSE
Requires-Dist: Pillow
Requires-Dist: numpy
Requires-Dist: click
Provides-Extra: ui
Requires-Dist: gradio>=4.0; extra == "ui"
Provides-Extra: opencv
Requires-Dist: opencv-python-headless; extra == "opencv"
Provides-Extra: audio
Requires-Dist: soundfile; extra == "audio"
Provides-Extra: ml
Requires-Dist: scikit-learn; extra == "ml"
Provides-Extra: full
Requires-Dist: gradio>=4.0; extra == "full"
Requires-Dist: opencv-python-headless; extra == "full"
Requires-Dist: soundfile; extra == "full"
Requires-Dist: scikit-learn; extra == "full"
Dynamic: license-file
